tranfort/__init__.py
tranfort-0.1.0.dist-info/WHEEL
tranfort-0.1.0.dist-info/METADATA
tranfort-0.1.0.dist-info/RECORD
