Metadata-Version: 2.1
Name: tranfort
Version: 0.1.0
Summary: Transformer for Tabular Data Learning
Author: yajiez
Author-email: yajiez.me@gmail.com
Requires-Python: >=3.7,<4.0
Classifier: Programming Language :: Python :: 3
Classifier: Programming Language :: Python :: 3.7
Classifier: Programming Language :: Python :: 3.8
Requires-Dist: matplotlib (>=3.1.2,<4.0.0)
Requires-Dist: numpy (>=1.18.1,<2.0.0)
Requires-Dist: pandas (>=0.25.3,<0.26.0)
Requires-Dist: scikit-learn (>=0.22.1,<0.23.0)
Requires-Dist: torch (>=1.4.0,<2.0.0)
Requires-Dist: transformers (>=2.3.0,<3.0.0)
